esayRedis/__init__.py
esayRedis-0.3.4.dist-info/METADATA
esayRedis-0.3.4.dist-info/WHEEL
esayRedis-0.3.4.dist-info/top_level.txt
esayRedis-0.3.4.dist-info/RECORD
