Metadata-Version: 2.1
Name: esayRedis
Version: 0.3.4
Summary: esayRedisTest
Home-page: http://example.com
Author: q2536807
Author-email: 616566665@qq.com
License: UNKNOWN
Platform: any
Requires-Dist: fastapi
Requires-Dist: aredis
Requires-Dist: starlette
Requires-Dist: pydantic
Requires-Dist: uuid
Requires-Dist: asyncio
